netrun/env/__init__.py
netrun/env/cli.py
netrun/env/diff.py
netrun/env/py.typed
netrun/env/schema.py
netrun/env/security.py
netrun/env/validator.py
netrun_env/__init__.py
netrun_env/cli.py
netrun_env/diff.py
netrun_env/schema.py
netrun_env/security.py
netrun_env/validator.py
netrun_env-2.1.0.dist-info/METADATA
netrun_env-2.1.0.dist-info/WHEEL
netrun_env-2.1.0.dist-info/entry_points.txt
netrun_env-2.1.0.dist-info/licenses/LICENSE
netrun_env-2.1.0.dist-info/RECORD
